amazon_scraper_by_outscraper/__init__.py
amazon_scraper_by_outscraper/client.py
amazon_scraper_by_outscraper/utils.py
amazon_scraper_by_outscraper-0.0.3.dist-info/LICENSE
amazon_scraper_by_outscraper-0.0.3.dist-info/METADATA
amazon_scraper_by_outscraper-0.0.3.dist-info/WHEEL
amazon_scraper_by_outscraper-0.0.3.dist-info/top_level.txt
amazon_scraper_by_outscraper-0.0.3.dist-info/RECORD
