Metadata-Version: 2.1
Name: amazon-scraper-by-outscraper
Version: 0.0.3
Summary: Amazon Scraper API SDK
Home-page: https://github.com/outscraper/amazon-scraper-python
Author: Outscraper
Author-email: developers@outscraper.com
License: MIT
Keywords: amazon reviews api sdk scraper parser extractor
Platform: UNKNOWN
Classifier: Programming Language :: Python
Classifier: License :: OSI Approved :: MIT License
Classifier: Operating System :: OS Independent
Classifier: Intended Audience :: Developers
Classifier: Topic :: Utilities
License-File: LICENSE
Requires-Dist: requests
